dsd/__init__.py
dsd/dsp.py
dsd/fibheap.py
dsd/metrics.py
dsd-0.0.3.dist-info/LICENSE
dsd-0.0.3.dist-info/METADATA
dsd-0.0.3.dist-info/WHEEL
dsd-0.0.3.dist-info/top_level.txt
dsd-0.0.3.dist-info/RECORD
