Metadata-Version: 2.1
Name: dsd
Version: 0.0.3
Summary: Dense subgraph discovery
Home-page: https://github.com/tsourakakis-lab
Author: C.E. Tsourakakis and Tianyi Chen
Author-email: graphminingtoolbox@gmail.com
License: UNKNOWN
Project-URL: Bug Tracker, https://github.com/tsourolampis/dense-subgraph-discovery/
Platform: UNKNOWN
Classifier: Programming Language :: Python :: 3
Classifier: License :: OSI Approved :: MIT License
Classifier: Operating System :: OS Independent
Requires-Python: >=3.0
License-File: LICENSE
Requires-Dist: networkx
